[
  {
    "init": [
      [
        200000001,
        50000
      ],
      [
        200003115,
        1
      ],
      [
        200000100,
        1
      ]
    ],
    "default_cannon": 20000,
    "old_compensate_max_gun": 250000,
    "default_gun": 200003115,
    "chest_count_down": 600,
    "chest_boss_ids": [
      100000401,
      100000402,
      100000407,
      100000404,
      100000405,
      100000403,
      100000406,
      100000408,
      100000410,
      100000318,
      100000411,
      100000412,
      100000416,
      100000414,
      100000317,
      100000322,
      100000323,
      100000417
    ],
    "disable_skill_time": 15,
    "call_fish_ID": [
      100000101,
      100000102,
      100000103,
      100000104,
      100000105,
      100000106,
      100000107,
      100000108,
      100000109,
      100000110,
      100000111
    ],
    "call_fish_road": [
      1
    ],
    "record_log_fish": 200,
    "lock_consumption": 1,
    "assets_item": [
      200000035,
      200000021,
      200000022,
      200000023
    ],
    "kill_fish_value": 10000000,
    "facai_gold_times": [
      0,
      60,
      120,
      180,
      240,
      300,
      300
    ],
    "time_shop_refresh": [
      5,
      10,
      15,
      20
    ],
    "time_shop_refresh_time": 14400,
    "realname": [
      [
        200008160,
        1
      ],
      [
        200000001,
        100000
      ],
      [
        200000002,
        20
      ],
      [
        200000003,
        2
      ],
      [
        200000004,
        2
      ]
    ],
    "no_realname": [
      [
        200000001,
        100000
      ]
    ],
    "repurchase_notice_mul": 10,
    "face_change": [
      1,
      2,
      3,
      4,
      5
    ],
    "arrangement_limit": 50000,
    "frozen_probability": 70,
    "frozen_probability_1": [
      60,
      40
    ],
    "frozen_max_num": 50,
    "fish_dish_first": 40,
    "fish_dish_additional": [
      [
        0,
        99,
        1
      ],
      [
        100,
        299,
        2
      ],
      [
        300,
        599,
        3
      ],
      [
        600,
        999,
        4
      ],
      [
        1000,
        100000,
        5
      ]
    ],
    "first_week_value": 299,
    "tomorrow_gif_value": 20,
    "new_player_gif": [
      [
        200000001,
        5000
      ],
      [
        200000002,
        2
      ],
      [
        200000003,
        2
      ],
      [
        200000004,
        2
      ]
    ],
    "charge_add_percent": 4000,
    "benefits_subsidies": [
      [
        1,
        2000000
      ],
      [
        4,
        3000000
      ]
    ],
    "new_player_subsidies": 2000000,
    "bankruptcy_subsidies_chance": [
      [
        20,
        2000
      ],
      [
        40,
        1500
      ],
      [
        999999999,
        1000
      ]
    ],
    "subsidies_add_value": 1000000,
    "new_max_gold": 200000,
    "lockAdition": [
      [
        102,
        3200,
        102,
        2800,
        102,
        2000,
        102,
        2000
      ],
      [
        101,
        3200,
        101,
        3000,
        101,
        2100,
        101,
        1700
      ],
      [
        100,
        3300,
        100,
        3000,
        100,
        2100,
        100,
        1600
      ]
    ],
    "ViolentAdition2": [
      [
        200,
        5000,
        200,
        5000
      ],
      [
        200,
        5000,
        200,
        5000
      ],
      [
        200,
        5000,
        200,
        5000
      ],
      [
        200,
        5000,
        200,
        5000
      ]
    ],
    "ViolentAdition4": [
      [
        300,
        5000,
        300,
        5000
      ],
      [
        300,
        5000,
        300,
        5000
      ],
      [
        300,
        5000,
        300,
        5000
      ],
      [
        300,
        5000,
        300,
        5000
      ]
    ],
    "ViolentAdition6": [
      [
        400,
        5000,
        400,
        5000
      ],
      [
        400,
        5000,
        400,
        5000
      ],
      [
        400,
        5000,
        400,
        5000
      ],
      [
        400,
        5000,
        400,
        5000
      ]
    ],
    "antiaddiction": 3600,
    "minors_game_time": 5400,
    "new_guide_max_gold": 200000,
    "free_fish_list": [
      1,
      2,
      3,
      4
    ],
    "drop_skill_value": 5,
    "gif_reset_time": 6,
    "phone_reward": [
      [
        200000001,
        300000
      ],
      [
        200000002,
        10
      ],
      [
        200000003,
        20
      ],
      [
        200000004,
        20
      ]
    ],
    "icon_sort": [
      1,
      2,
      3
    ],
    "god_pig_proportion": 500,
    "growth_fund_max": "10亿",
    "luxuriousroom_unlock": 18,
    "luxuriousroom_guide": 30000000,
    "violent_bonus": [
      [
        2,
        2,
        3,
        4
      ]
    ],
    "Repurchase_chargetype": [
      2,
      3,
      4,
      5,
      8,
      10,
      12,
      14,
      16,
      18,
      20
    ],
    "preferential_gif_sorting": [
      [
        0,
        830005011,
        830005013,
        830005014,
        830005015
      ],
      [
        3,
        830005013,
        830005014,
        830005015,
        830005017
      ],
      [
        5,
        830005014,
        830005015,
        830005017,
        830005018
      ]
    ],
    "preferential_gif_sorting_io": [
      [
        0,
        830005011,
        830005013,
        830005014,
        830005015
      ],
      [
        3,
        830005013,
        830005014,
        830005015,
        830005017
      ],
      [
        5,
        830005014,
        830005015,
        830005017,
        830005018
      ]
    ],
    "preferential_gif_default": [
      830005013,
      830005013,
      830005013,
      830005015,
      830005015,
      830005017,
      830005017,
      830005017,
      830005017,
      830005017
    ],
    "growth_fund_reward": [
      20,
      0
    ],
    "preferential_gif_default_io": [
      830005013,
      830005013,
      830005013,
      830005015,
      830005015,
      830005017,
      830005017,
      830005017,
      830005017,
      830005017
    ],
    "yinyang_times": [
      [
        0,
        1900
      ],
      [
        1,
        2600
      ],
      [
        2,
        2600
      ],
      [
        3,
        2500
      ],
      [
        4,
        400
      ]
    ],
    "yinyang_num": [
      [
        5,
        10,
        10000
      ]
    ],
    "yinyang_rate": [
      [
        20,
        30,
        2600
      ],
      [
        30,
        40,
        3000
      ],
      [
        40,
        50,
        2500
      ],
      [
        50,
        60,
        1400
      ],
      [
        60,
        90,
        500
      ]
    ],
    "yinyang_gold": 20,
    "yinyang_goldrate": [
      [
        2,
        5000
      ],
      [
        3,
        3000
      ],
      [
        4,
        2000
      ]
    ],
    "mysticaltable_times": [
      [
        2,
        3000
      ],
      [
        4,
        1000
      ],
      [
        3,
        3000
      ],
      [
        6,
        1000
      ],
      [
        5,
        1000
      ],
      [
        8,
        1000
      ]
    ],
    "mysticaltable_1": [
      [
        200000004,
        5,
        1250
      ],
      [
        200000035,
        1,
        1250
      ],
      [
        200000017,
        2,
        1250
      ],
      [
        200000002,
        5,
        1250
      ],
      [
        200000003,
        5,
        1250
      ],
      [
        200000001,
        200000,
        1250
      ],
      [
        200000005,
        5,
        1250
      ],
      [
        200000001,
        400000,
        1250
      ]
    ],
    "mysticaltable_2": [
      [
        200000002,
        50,
        1000
      ],
      [
        200000001,
        2000000,
        1000
      ],
      [
        200000021,
        5,
        1000
      ],
      [
        200000035,
        2,
        1000
      ],
      [
        200000003,
        30,
        1000
      ],
      [
        200000035,
        10,
        1000
      ],
      [
        200000001,
        4000000,
        1000
      ],
      [
        200000004,
        20,
        1000
      ],
      [
        200000021,
        2,
        1000
      ],
      [
        200000017,
        10,
        1000
      ]
    ],
    "mysticaltable_3": [
      [
        200000002,
        100,
        1000
      ],
      [
        200000021,
        10,
        1000
      ],
      [
        200000001,
        5000000,
        1000
      ],
      [
        200000017,
        15,
        1000
      ],
      [
        200000022,
        2,
        1000
      ],
      [
        200000003,
        30,
        1000
      ],
      [
        200000022,
        5,
        1000
      ],
      [
        200000021,
        2,
        1000
      ],
      [
        200000004,
        40,
        1000
      ],
      [
        200000001,
        8000000,
        1000
      ]
    ],
    "icedragon_frozen": 4.2,
    "return_reward": [
      [
        200000001,
        1000000
      ],
      [
        200000002,
        100
      ],
      [
        200000003,
        20
      ],
      [
        200000004,
        20
      ]
    ],
    "regress_day": 7,
    "shenqishop_discount": [
      [
        0,
        9
      ],
      [
        1,
        8.5
      ],
      [
        2,
        8
      ],
      [
        3,
        7
      ]
    ],
    "shenqishop_refresh_price": [
      200000002,
      20
    ],
    "shenqishop_day_limit": 2,
    "invited_reward": [
      [
        200000035,
        1
      ],
      [
        200000002,
        10
      ],
      [
        200000004,
        5
      ],
      [
        200000005,
        5
      ]
    ],
    "wings_ad_shopid": [
      830003124,
      830003123,
      830003122,
      830003121
    ],
    "cheap_gift_day_limit": 4,
    "recharge_add_rate": [
      [
        0,
        100000,
        -100000,
        1000
      ],
      [
        100000,
        999999999,
        5000,
        1000
      ]
    ],
    "crazy_cowboy_rope_times": 2,
    "crazy_cowboy_base_reward": 240,
    "tortoise_base_reward": 0,
    "get_way_txt": "1,注册账号获得;2,炮台商店出售;3,时光宝库出售;4,新手礼包赠送;5,新手周卡赠送;6,贵族特权赠送;7,赛季补给获得;8,参与活动获得;9,五福临门活动获得",
    "download_reward": [
      [
        200000001,
        10000000
      ]
    ],
    "jadeDragon_rage": [
      3,
      50,
      2
    ],
    "pearl_no_kill": [
      100000352,
      100000353,
      100000354,
      100000355,
      100000357,
      100000361,
      100000362,
      100000363,
      100000364,
      100000365,
      100000366,
      100000367,
      100000371,
      100000372,
      100000373,
      100000374,
      100000375,
      100000376,
      100000377,
      100000378,
      100000379,
      100000380,
      100000381,
      100000382,
      100000385,
      100000387,
      100000388,
      100000389,
      100000413,
      100000414,
      100000415,
      100000421,
      100000422,
      100000427,
      100000501,
      100000503,
      100001352,
      100001353,
      100001354,
      100001355,
      100001357,
      100001361,
      100001362,
      100001363,
      100001364,
      100001365,
      100001366,
      100001367,
      100001371,
      100001372,
      100001373,
      100001374,
      100001375,
      100001376,
      100001377,
      100001378,
      100001379,
      100001380,
      100001381,
      100001382,
      100001385,
      100001387,
      100001388,
      100001389,
      100001501,
      100001503,
      100001413,
      100001414,
      100001415,
      100001421,
      100001422,
      100001427,
      100002352,
      100002353,
      100002354,
      100002355,
      100002357,
      100002361,
      100002362,
      100002363,
      100002364,
      100002365,
      100002366,
      100002367,
      100002371,
      100002372,
      100002373,
      100002374,
      100002375,
      100002376,
      100002377,
      100002378,
      100002379,
      100002380,
      100002381,
      100002382,
      100002385,
      100002387,
      100002388,
      100002389,
      100002501,
      100002503,
      100002413,
      100002414,
      100002415,
      100002421,
      100002422,
      100002427,
      100001386,
      100000386
    ],
    "skills_suspend_time": 5,
    "drop_god_skill_fish": [
      100000352,
      100000353,
      100000354,
      100000355,
      100000362,
      100000363,
      100000379,
      100000380,
      100001352,
      100001353,
      100001354,
      100001355,
      100001362,
      100001363,
      100001379,
      100001380,
      100002352,
      100002353,
      100002354,
      100002355,
      100002362,
      100002363,
      100002379,
      100002380
    ],
    "drop_ansab_fish": [
      100000361,
      100000362,
      100000363,
      100000364,
      100000365,
      100000367,
      100000371,
      100000372,
      100000373,
      100000374,
      100000375,
      100000376,
      100000378,
      100000379,
      100000380,
      100000381,
      100000421,
      100000422,
      100001352,
      100001353,
      100001354,
      100001355,
      100001421,
      100001422,
      100001361,
      100001362,
      100001363,
      100001364,
      100001365,
      100001367,
      100001371,
      100001372,
      100001373,
      100001374,
      100001375,
      100001376,
      100001378,
      100001379,
      100001380,
      100001381,
      100002352,
      100002353,
      100002354,
      100002355,
      100002421,
      100002422,
      100002361,
      100002362,
      100002363,
      100002364,
      100002365,
      100002367,
      100002371,
      100002372,
      100002373,
      100002374,
      100002375,
      100002376,
      100002378,
      100002379,
      100002380,
      100002381
    ],
    "drop_pearl_fish": [
      100000372,
      100000362,
      100001372,
      100001362
    ],
    "pearl_cd": 20,
    "new_rate_day": 3,
    "new_rate_value": 100000,
    "new_conversion_code_day": 3,
    "cai_shen_no_killer_reward": 70,
    "eat_all_ID": [
      100001313,
      100000313
    ],
    "eat_all_true_score": [
      [
        1000,
        2000
      ],
      [
        1500,
        10000
      ]
    ],
    "eat_all_reward_rate": [
      [
        1000,
        3000
      ],
      [
        1500,
        10000
      ]
    ],
    "focus_reward": [
      [
        200000001,
        500000
      ],
      [
        200000002,
        10
      ],
      [
        200000003,
        5
      ],
      [
        200000004,
        5
      ],
      [
        200000005,
        5
      ],
      [
        200000035,
        5
      ]
    ],
    "focus_red_time": "2022-02-07 23:00:00",
    "public_rotary_day_reward": [
      [
        200000001,
        20000,
        5
      ],
      [
        200000001,
        50000,
        5
      ],
      [
        200000001,
        80000,
        30
      ],
      [
        200000001,
        100000,
        30
      ],
      [
        200000001,
        200000,
        10
      ],
      [
        200000002,
        20,
        5
      ],
      [
        200000021,
        1,
        5
      ],
      [
        200008160,
        1,
        10
      ]
    ],
    "public_rotary_week_reward": [
      [
        200000001,
        500000,
        5
      ],
      [
        200000001,
        800000,
        10
      ],
      [
        200000001,
        1000000,
        10
      ],
      [
        200000001,
        2000000,
        25
      ],
      [
        200000001,
        5000000,
        5
      ],
      [
        200000021,
        5,
        5
      ],
      [
        200008161,
        1,
        20
      ],
      [
        200003188,
        1,
        20
      ]
    ],
    "xi_you_skill_type": [
      0,
      2
    ],
    "xi_you_skill_chance": 1000,
    "xi_you_skill_cd": 30,
    "download_open_time": "2022-02-16 00:00:00",
    "prompt_ratio": 50,
    "prompt_times": 3,
    "shen_qi_name": "幽冥白骨;虎力大仙;无双战神;火烧赤壁",
    "drop_cannon": 20000,
    "shen_qi_sorting": [
      0,
      2,
      1,
      3
    ],
    "drop_forging_id": [
      200000103,
      200000104,
      200000105,
      200000106
    ],
    "shen_qi_must_success": 5,
    "shenqishop_day_refresh": 30,
    "time_shop_day_refresh": 30
  }
]